{
  "text": "{\"file_path\":\"\\/mnt\\/data\\/split_trophy_car_seat.webp\",\"snapshot_handle\":\"GJk-AiCpWgAR1aQDADIopeUb9Lprbg1iAQBj\",\"status\":\"Generated 1 image(s)\",\"tools_called_tag\":\"\\n[tools_called: generate_image]\",\"media_context_handle\":\"r3q205\"}",
  "attachments": [
    {
      "url": "https://scontent.xx.fbcdn.net/v/t39.105495-1/740343473_1412465104273325_1934512749265816566_n.webp?_nc_ht=scontent.xx.fbcdn.net&_nc_cat=105&_nc_ohc=8ukOvrj6ZPQQ7kNvwGuVZ0j&sdl=0&ccb=14-4&oh=00_AQB2H-vHtqrFM_IgVIGJWDfm8Q6PU6rnvsowxEPyTeIkMQ&oe=6A536792&_nc_sid=a21977",
      "media_handle": ""
    }
  ]
}